netcat/__init__.py
netcat/netcat.py
netcat_python-0.1.0.dist-info/LICENSE.txt
netcat_python-0.1.0.dist-info/METADATA
netcat_python-0.1.0.dist-info/WHEEL
netcat_python-0.1.0.dist-info/top_level.txt
netcat_python-0.1.0.dist-info/RECORD
