Metadata-Version: 2.1
Name: netcat_python
Version: 0.1.0
Summary: This is an netcat Replacer Build on Python language.
Home-page: https://www.github.com/MyFaduGame/netcat_python
Author: MyFaduGame
Author-email: navinsharma9376319931@gmail.com
Project-URL: Bug Tracker, https://www.github.com/MyFaduGame/
Classifier: Programming Language :: Python :: 3
Classifier: License :: OSI Approved :: MIT License
Classifier: Operating System :: OS Independent
Requires-Python: >=3.6
License-File: LICENSE.txt
